coordgeompy/__init__.py
coordgeompy/coordgeompy.py
coordgeompy-1.0.10.dist-info/LICENSE
coordgeompy-1.0.10.dist-info/WHEEL
coordgeompy-1.0.10.dist-info/METADATA
coordgeompy-1.0.10.dist-info/RECORD
