Metadata-Version: 2.1
Name: coordgeompy
Version: 1.0.10
Summary: A simple coordinate geometry helper package
License: MIT
Author: Jordan Casoli, Nico Van Den Hooff, Arlin Cherian and Zheren Xu
Requires-Python: >=3.9,<4.0
Classifier: License :: OSI Approved :: MIT License
Classifier: Programming Language :: Python :: 3
Classifier: Programming Language :: Python :: 3.10
Classifier: Programming Language :: Python :: 3.9
Requires-Dist: numpy (>=1.22.1,<2.0.0)
